fluxbind/__init__.py
fluxbind/version.py
fluxbind/bind/__init__.py
fluxbind/bind/bind.py
fluxbind/cli/__init__.py
fluxbind/cli/help.py
fluxbind/cli/predict.py
fluxbind/cli/run.py
fluxbind/cli/shape.py
fluxbind/logger/__init__.py
fluxbind/logger/generate.py
fluxbind/logger/logger.py
fluxbind/scripts/report_mapping.sh
fluxbind/scripts/run_mapping.sh
fluxbind/shape/__init__.py
fluxbind/shape/shape.py
fluxbind/topology/__init__.py
fluxbind/topology/predict.py
fluxbind/utils/__init__.py
fluxbind/utils/fileio.py
fluxbind/utils/timer.py
fluxbind-0.0.1.dist-info/LICENSE
fluxbind-0.0.1.dist-info/METADATA
fluxbind-0.0.1.dist-info/NOTICE
fluxbind-0.0.1.dist-info/WHEEL
fluxbind-0.0.1.dist-info/entry_points.txt
fluxbind-0.0.1.dist-info/top_level.txt
fluxbind-0.0.1.dist-info/RECORD
