Metadata-Version: 2.1
Name: fluxbind
Version: 0.0.1
Summary: Process mapping for Flux jobs
Home-page: https://github.com/compspec/fluxbind
Author: Vanessa Sochat
Author-email: vsoch@users.noreply.github.com
Maintainer: Vanessa Sochat
License: LICENSE
Keywords: cluster,orchestration,mpi,binding,topology
Classifier: Intended Audience :: Science/Research
Classifier: Intended Audience :: Developers
Classifier: License :: OSI Approved :: Mozilla Public License 2.0 (MPL 2.0)
Classifier: Programming Language :: C
Classifier: Programming Language :: Python
Classifier: Topic :: Software Development
Classifier: Topic :: Scientific/Engineering
Classifier: Operating System :: Unix
Classifier: Programming Language :: Python :: 3.11
License-File: LICENSE
License-File: NOTICE
Requires-Dist: jsonschema
Requires-Dist: Jinja2
Requires-Dist: rich
Provides-Extra: all
Requires-Dist: jsonschema ; extra == 'all'
Requires-Dist: Jinja2 ; extra == 'all'
Requires-Dist: rich ; extra == 'all'
Requires-Dist: pytest >=4.6.2 ; extra == 'all'
